CheckMethod/Check.py
CheckMethod/ReadXml.py
CheckMethod/__init__.py
CheckMethod-1.3.3.dist-info/DESCRIPTION.rst
CheckMethod-1.3.3.dist-info/METADATA
CheckMethod-1.3.3.dist-info/RECORD
CheckMethod-1.3.3.dist-info/WHEEL
CheckMethod-1.3.3.dist-info/metadata.json
CheckMethod-1.3.3.dist-info/top_level.txt
