Metadata-Version: 2.0
Name: CheckMethod
Version: 1.3.3
Summary: 飞马主柜台上场文件合规检测
Home-page: http://www.mirrorcffex.cn
Author: WangZhp
Author-email: huoyingkk@163.com
Maintainer: WangZhp
Maintainer-email: huoyingkk@163.com
License: BSD License
Platform: all
Classifier: License :: OSI Approved :: BSD License
Classifier: Programming Language :: Python :: 3.6
Requires-Dist: pandas (>=0.22.0)
Requires-Dist: paramiko (>=2.4.2)
